[
    {
        "worldSetNo": 1,
        "routeId": 100010,
        "imgId": 100010,
        "posX": 728,
        "posY": 230,
        "flag1Id": 999999,
        "flag2Id": 0,
        "flag3Id": 0,
        "searchText": "北土"
    },
    {
        "worldSetNo": 1,
        "routeId": 100020,
        "imgId": 100020,
        "posX": 2114,
        "posY": 1355,
        "flag1Id": 999999,
        "flag2Id": 0,
        "flag3Id": 0,
        "searchText": "USA_アオテアロア_タヒチ"
    },
    {
        "worldSetNo": 1,
        "routeId": 100030,
        "imgId": 100030,
        "posX": 1054,
        "posY": 736,
        "flag1Id": 31004021,
        "flag2Id": 0,
        "flag3Id": 0,
        "searchText": "USA_インド"
    },
    {
        "worldSetNo": 1,
        "routeId": 100040,
        "imgId": 100040,
        "posX": 1307,
        "posY": 857,
        "flag1Id": 999999,
        "flag2Id": 0,
        "flag3Id": 0,
        "searchText": "USA_カルカッタ_アユタヤ"
    },
    {
        "worldSetNo": 1,
        "routeId": 100050,
        "imgId": 100050,
        "posX": 2193,
        "posY": 598,
        "flag1Id": 31007021,
        "flag2Id": 0,
        "flag3Id": 0,
        "searchText": "USA_サンフランシスコ_ハワイ"
    },
    {
        "worldSetNo": 1,
        "routeId": 100060,
        "imgId": 100060,
        "posX": 2169,
        "posY": 800,
        "flag1Id": 999999,
        "flag2Id": 0,
        "flag3Id": 0,
        "searchText": "USA_タヒチ_ハワイ"
    },
    {
        "worldSetNo": 1,
        "routeId": 100070,
        "imgId": 100070,
        "posX": 2597,
        "posY": 675,
        "flag1Id": 31007091,
        "flag2Id": 0,
        "flag3Id": 0,
        "searchText": "USA_チワワ_テオティワカン"
    },
    {
        "worldSetNo": 1,
        "routeId": 100080,
        "imgId": 100080,
        "posX": 2785,
        "posY": 858,
        "flag1Id": 31008041,
        "flag2Id": 0,
        "flag3Id": 0,
        "searchText": "USA_パナマ_キト"
    },
    {
        "worldSetNo": 1,
        "routeId": 100090,
        "imgId": 100090,
        "posX": -539,
        "posY": 312,
        "flag1Id": 999999,
        "flag2Id": 0,
        "flag3Id": 0,
        "searchText": "USA_ブリタニア"
    },
    {
        "worldSetNo": 1,
        "routeId": 100100,
        "imgId": 100100,
        "posX": 3005,
        "posY": 312,
        "flag1Id": 999999,
        "flag2Id": 0,
        "flag3Id": 0,
        "searchText": "USA_ブリタニアa"
    },
    {
        "worldSetNo": 1,
        "routeId": 100110,
        "imgId": 100110,
        "posX": 270,
        "posY": 630,
        "flag1Id": 999999,
        "flag2Id": 0,
        "flag3Id": 0,
        "searchText": "USA_暗黒領域"
    },
    {
        "worldSetNo": 1,
        "routeId": 100120,
        "imgId": 100120,
        "posX": -544,
        "posY": 203,
        "flag1Id": 999999,
        "flag2Id": 0,
        "flag3Id": 0,
        "searchText": "USA_欧州"
    },
    {
        "worldSetNo": 1,
        "routeId": 100130,
        "imgId": 100130,
        "posX": 3000,
        "posY": 203,
        "flag1Id": 999999,
        "flag2Id": 0,
        "flag3Id": 0,
        "searchText": "USA_欧州a"
    },
    {
        "worldSetNo": 1,
        "routeId": 100140,
        "imgId": 100140,
        "posX": 1489,
        "posY": 1242,
        "flag1Id": 999999,
        "flag2Id": 0,
        "flag3Id": 0,
        "searchText": "USA_豪州"
    },
    {
        "worldSetNo": 1,
        "routeId": 100150,
        "imgId": 100150,
        "posX": 1731,
        "posY": 726,
        "flag1Id": 31006011,
        "flag2Id": 0,
        "flag3Id": 0,
        "searchText": "USA_邪馬台_グァム"
    },
    {
        "worldSetNo": 1,
        "routeId": 100160,
        "imgId": 100160,
        "posX": 1644,
        "posY": 487,
        "flag1Id": 31003011,
        "flag2Id": 0,
        "flag3Id": 0,
        "searchText": "USA_邪馬台_ザナドゥ"
    },
    {
        "worldSetNo": 1,
        "routeId": 100170,
        "imgId": 100170,
        "posX": 1574,
        "posY": 727,
        "flag1Id": 31002051,
        "flag2Id": 0,
        "flag3Id": 0,
        "searchText": "USA_邪馬台_香港"
    },
    {
        "worldSetNo": 1,
        "routeId": 100180,
        "imgId": 100180,
        "posX": 1661,
        "posY": 725,
        "flag1Id": 31002011,
        "flag2Id": 0,
        "flag3Id": 0,
        "searchText": "USA_邪馬台_上海"
    },
    {
        "worldSetNo": 1,
        "routeId": 100190,
        "imgId": 100190,
        "posX": 1858,
        "posY": 597,
        "flag1Id": 999999,
        "flag2Id": 0,
        "flag3Id": 0,
        "searchText": "USA_仙台_サンフランシスコ"
    },
    {
        "worldSetNo": 1,
        "routeId": 100200,
        "imgId": 100200,
        "posX": 1289,
        "posY": 527,
        "flag1Id": 31002021,
        "flag2Id": 0,
        "flag3Id": 0,
        "searchText": "USA_大華帝国"
    },
    {
        "worldSetNo": 1,
        "routeId": 100210,
        "imgId": 100210,
        "posX": 851,
        "posY": 659,
        "flag1Id": 999999,
        "flag2Id": 0,
        "flag3Id": 0,
        "searchText": "USA_中東"
    },
    {
        "worldSetNo": 1,
        "routeId": 100220,
        "imgId": 100220,
        "posX": 2852,
        "posY": 1222,
        "flag1Id": 999999,
        "flag2Id": 0,
        "flag3Id": 0,
        "searchText": "USA_南米_大西洋"
    },
    {
        "worldSetNo": 1,
        "routeId": 100240,
        "imgId": 100240,
        "posX": 2284,
        "posY": 246,
        "flag1Id": 31007031,
        "flag2Id": 0,
        "flag3Id": 0,
        "searchText": "USA_北米１"
    },
    {
        "worldSetNo": 1,
        "routeId": 100250,
        "imgId": 100250,
        "posX": 2607,
        "posY": 550,
        "flag1Id": 31007041,
        "flag2Id": 0,
        "flag3Id": 0,
        "searchText": "USA_北米２"
    },
    {
        "worldSetNo": 1,
        "routeId": 100260,
        "imgId": 100260,
        "posX": 2757,
        "posY": 525,
        "flag1Id": 31007081,
        "flag2Id": 0,
        "flag3Id": 0,
        "searchText": "USA_北米３"
    },
    {
        "worldSetNo": 1,
        "routeId": 100270,
        "imgId": 100270,
        "posX": 2835,
        "posY": 730,
        "flag1Id": 999999,
        "flag2Id": 0,
        "flag3Id": 0,
        "searchText": "ヴィンランド"
    },
    {
        "worldSetNo": 1,
        "routeId": 100280,
        "imgId": 100280,
        "posX": 585,
        "posY": 772,
        "flag1Id": 999999,
        "flag2Id": 0,
        "flag3Id": 0,
        "searchText": "エジプト"
    },
    {
        "worldSetNo": 1,
        "routeId": 100290,
        "imgId": 100290,
        "posX": 640,
        "posY": 725,
        "flag1Id": 999999,
        "flag2Id": 0,
        "flag3Id": 0,
        "searchText": "エジプト２"
    },
    {
        "worldSetNo": 1,
        "routeId": 100300,
        "imgId": 100300,
        "posX": 3168,
        "posY": 614,
        "flag1Id": 999999,
        "flag2Id": 0,
        "flag3Id": 0,
        "searchText": "エリュシオン_アトランティス"
    },
    {
        "worldSetNo": 1,
        "routeId": 100310,
        "imgId": 100310,
        "posX": 2984,
        "posY": 772,
        "flag1Id": 999999,
        "flag2Id": 0,
        "flag3Id": 0,
        "searchText": "サントドミンゴ_エリュシオン"
    },
    {
        "worldSetNo": 1,
        "routeId": 100320,
        "imgId": 100320,
        "posX": 1732,
        "posY": 624,
        "flag1Id": 31001021,
        "flag2Id": 0,
        "flag3Id": 0,
        "searchText": "ジパング"
    },
    {
        "worldSetNo": 1,
        "routeId": 100330,
        "imgId": 100330,
        "posX": 568,
        "posY": 166,
        "flag1Id": 999999,
        "flag2Id": 0,
        "flag3Id": 0,
        "searchText": "ストックホルム_ヒュペルボレイオス"
    },
    {
        "worldSetNo": 1,
        "routeId": 100340,
        "imgId": 100340,
        "posX": 2577,
        "posY": 508,
        "flag1Id": 999999,
        "flag2Id": 0,
        "flag3Id": 0,
        "searchText": "ソルトレイクシティ_エルピス_ＵＳＡ"
    },
    {
        "worldSetNo": 1,
        "routeId": 100350,
        "imgId": 100350,
        "posX": 322,
        "posY": 268,
        "flag1Id": 31010011,
        "flag2Id": 0,
        "flag3Id": 0,
        "searchText": "ブリタニア"
    },
    {
        "worldSetNo": 1,
        "routeId": 100360,
        "imgId": 100360,
        "posX": 1021,
        "posY": 917,
        "flag1Id": 999999,
        "flag2Id": 0,
        "flag3Id": 0,
        "searchText": "ムンバイ_ドワール・カー"
    },
    {
        "worldSetNo": 1,
        "routeId": 100370,
        "imgId": 100370,
        "posX": 1037,
        "posY": 462,
        "flag1Id": 31003041,
        "flag2Id": 0,
        "flag3Id": 0,
        "searchText": "ルート_アルマリク_ウルゲンチ"
    },
    {
        "worldSetNo": 1,
        "routeId": 100380,
        "imgId": 100380,
        "posX": 1989,
        "posY": 287,
        "flag1Id": 999999,
        "flag2Id": 0,
        "flag3Id": 0,
        "searchText": "ルート_アンカレジ_カムチャッキー"
    },
    {
        "worldSetNo": 1,
        "routeId": 100390,
        "imgId": 100390,
        "posX": 687,
        "posY": 562,
        "flag1Id": 999999,
        "flag2Id": 0,
        "flag3Id": 0,
        "searchText": "ルート_コンスタンティノープル_ゴルディオン"
    },
    {
        "worldSetNo": 1,
        "routeId": 100400,
        "imgId": 100400,
        "posX": 678,
        "posY": 193,
        "flag1Id": 999999,
        "flag2Id": 0,
        "flag3Id": 0,
        "searchText": "ルート_サンクトペテルブルグ_ヘルシンキ"
    },
    {
        "worldSetNo": 1,
        "routeId": 100410,
        "imgId": 100410,
        "posX": 2834,
        "posY": 550,
        "flag1Id": 999999,
        "flag2Id": 0,
        "flag3Id": 0,
        "searchText": "ルート_ニューヨーク_ハバナ"
    },
    {
        "worldSetNo": 1,
        "routeId": 100420,
        "imgId": 100420,
        "posX": 587,
        "posY": 849,
        "flag1Id": 999999,
        "flag2Id": 0,
        "flag3Id": 0,
        "searchText": "隠し_アアル"
    },
    {
        "worldSetNo": 1,
        "routeId": 100430,
        "imgId": 100430,
        "posX": 209,
        "posY": 267,
        "flag1Id": 999999,
        "flag2Id": 0,
        "flag3Id": 0,
        "searchText": "隠し_アヴァロン"
    },
    {
        "worldSetNo": 1,
        "routeId": 100440,
        "imgId": 100440,
        "posX": 318,
        "posY": 397,
        "flag1Id": 31011011,
        "flag2Id": 0,
        "flag3Id": 0,
        "searchText": "隠し_イース"
    },
    {
        "worldSetNo": 1,
        "routeId": 100450,
        "imgId": 100450,
        "posX": 2858,
        "posY": 1093,
        "flag1Id": 999999,
        "flag2Id": 0,
        "flag3Id": 0,
        "searchText": "隠し_エル・ドラードゲート"
    },
    {
        "worldSetNo": 1,
        "routeId": 100460,
        "imgId": 100460,
        "posX": 770,
        "posY": 531,
        "flag1Id": 999999,
        "flag2Id": 0,
        "flag3Id": 0,
        "searchText": "隠し_カイマクル"
    },
    {
        "worldSetNo": 1,
        "routeId": 100480,
        "imgId": 100480,
        "posX": 1017,
        "posY": 942,
        "flag1Id": 999999,
        "flag2Id": 0,
        "flag3Id": 0,
        "searchText": "隠し_クマリナドゥ"
    },
    {
        "worldSetNo": 1,
        "routeId": 100490,
        "imgId": 100490,
        "posX": 875,
        "posY": 455,
        "flag1Id": 999999,
        "flag2Id": 0,
        "flag3Id": 0,
        "searchText": "隠し_シャンバラ"
    },
    {
        "worldSetNo": 1,
        "routeId": 100500,
        "imgId": 100500,
        "posX": 483,
        "posY": 595,
        "flag1Id": 999999,
        "flag2Id": 0,
        "flag3Id": 0,
        "searchText": "隠し_シュオル"
    },
    {
        "worldSetNo": 1,
        "routeId": 100510,
        "imgId": 100510,
        "posX": 2155,
        "posY": 896,
        "flag1Id": 999999,
        "flag2Id": 0,
        "flag3Id": 0,
        "searchText": "隠し_ヒラニプラ"
    },
    {
        "worldSetNo": 1,
        "routeId": 100520,
        "imgId": 100520,
        "posX": 572,
        "posY": 90,
        "flag1Id": 999999,
        "flag2Id": 0,
        "flag3Id": 0,
        "searchText": "隠し_ポホヨラ"
    },
    {
        "worldSetNo": 1,
        "routeId": 100530,
        "imgId": 100530,
        "posX": 2995,
        "posY": 245,
        "flag1Id": 999999,
        "flag2Id": 0,
        "flag3Id": 0,
        "searchText": "隠し_マグ・メル"
    },
    {
        "worldSetNo": 1,
        "routeId": 100540,
        "imgId": 100540,
        "posX": 1732,
        "posY": 669,
        "flag1Id": 999999,
        "flag2Id": 0,
        "flag3Id": 0,
        "searchText": "隠し_竜宮"
    },
    {
        "worldSetNo": 1,
        "routeId": 100550,
        "imgId": 100550,
        "posX": 1668,
        "posY": 1232,
        "flag1Id": 999999,
        "flag2Id": 0,
        "flag3Id": 0,
        "searchText": "豪州"
    },
    {
        "worldSetNo": 1,
        "routeId": 100560,
        "imgId": 100560,
        "posX": 821,
        "posY": 717,
        "flag1Id": 999999,
        "flag2Id": 0,
        "flag3Id": 0,
        "searchText": "中東"
    },
    {
        "worldSetNo": 1,
        "routeId": 100570,
        "imgId": 100570,
        "posX": 2627,
        "posY": 723,
        "flag1Id": 31008011,
        "flag2Id": 0,
        "flag3Id": 0,
        "searchText": "南米"
    },
    {
        "worldSetNo": 1,
        "routeId": 100580,
        "imgId": 100580,
        "posX": 643,
        "posY": 463,
        "flag1Id": 999999,
        "flag2Id": 0,
        "flag3Id": 0,
        "searchText": "馬蒙連合"
    },
    {
        "worldSetNo": 1,
        "routeId": 100590,
        "imgId": 100590,
        "posX": 1275,
        "posY": 856,
        "flag1Id": 31004011,
        "flag2Id": 0,
        "flag3Id": 0,
        "searchText": "ルート_香港_カルカッタ"
    },
    {
        "worldSetNo": 1,
        "routeId": 100600,
        "imgId": 100600,
        "posX": 645,
        "posY": 547,
        "flag1Id": 999999,
        "flag2Id": 0,
        "flag3Id": 0,
        "searchText": "ルート_マケドニア"
    },
    {
        "worldSetNo": 1,
        "routeId": 100610,
        "imgId": 100610,
        "posX": 1058,
        "posY": 465,
        "flag1Id": 31003021,
        "flag2Id": 0,
        "flag3Id": 0,
        "searchText": "ルート_モンゴル"
    },
    {
        "worldSetNo": 1,
        "routeId": 100620,
        "imgId": 100620,
        "posX": 2834,
        "posY": 1387,
        "flag1Id": 31008061,
        "flag2Id": 0,
        "flag3Id": 0,
        "searchText": "ルート_バルパライソ_ブエノスアイレス"
    },
    {
        "worldSetNo": 1,
        "routeId": 100630,
        "imgId": 100630,
        "posX": 3042,
        "posY": 1226,
        "flag1Id": 31008061,
        "flag2Id": 0,
        "flag3Id": 0,
        "searchText": "ルート_ブエノスアイレス_リオデジャネイロ"
    },
    {
        "worldSetNo": 1,
        "routeId": 100640,
        "imgId": 100640,
        "posX": 250,
        "posY": 203,
        "flag1Id": 31009011,
        "flag2Id": 0,
        "flag3Id": 0,
        "searchText": "欧州"
    },
    {
        "worldSetNo": 1,
        "routeId": 100650,
        "imgId": 100650,
        "posX": 3205,
        "posY": 520,
        "flag1Id": 31008081,
        "flag2Id": 0,
        "flag3Id": 0,
        "searchText": "ルート_リオデジャネイロ_リスボン"
    },
    {
        "worldSetNo": 1,
        "routeId": 100660,
        "imgId": 100660,
        "posX": 1858,
        "posY": 624,
        "flag1Id": 31007011,
        "flag2Id": 0,
        "flag3Id": 0,
        "searchText": "ルート_仙台_ハワイ"
    },
    {
        "worldSetNo": 1,
        "routeId": 100670,
        "imgId": 100670,
        "posX": 1639,
        "posY": 480,
        "flag1Id": 999999,
        "flag2Id": 0,
        "flag3Id": 0,
        "searchText": "ルート_ザナドゥ_ウラジオストック"
    },
    {
        "worldSetNo": 1,
        "routeId": 100680,
        "imgId": 100680,
        "posX": 865,
        "posY": 840,
        "flag1Id": 31012031,
        "flag2Id": 0,
        "flag3Id": 0,
        "searchText": "隠し_エルピス_バベル"
    },
    {
        "worldSetNo": 1,
        "routeId": 100690,
        "imgId": 100690,
        "posX": 630,
        "posY": 590,
        "flag1Id": 31012011,
        "flag2Id": 0,
        "flag3Id": 0,
        "searchText": "ルート_ウルク_アテネ"
    },
    {
        "worldSetNo": 1,
        "routeId": 100700,
        "imgId": 100700,
        "posX": 821,
        "posY": 777,
        "flag1Id": 31012021,
        "flag2Id": 0,
        "flag3Id": 0,
        "searchText": "中東２"
    },
    {
        "worldSetNo": 1,
        "routeId": 100710,
        "imgId": 100710,
        "posX": 1485,
        "posY": 930,
        "flag1Id": 31006021,
        "flag2Id": 0,
        "flag3Id": 0,
        "searchText": "南洋２"
    },
    {
        "worldSetNo": 2,
        "routeId": 100010,
        "imgId": 100010,
        "posX": 728,
        "posY": 230,
        "flag1Id": 31123021,
        "flag2Id": 0,
        "flag3Id": 0,
        "searchText": "北土"
    },
    {
        "worldSetNo": 2,
        "routeId": 100020,
        "imgId": 100020,
        "posX": 2114,
        "posY": 1355,
        "flag1Id": 999999,
        "flag2Id": 0,
        "flag3Id": 0,
        "searchText": "USA_アオテアロア_タヒチ"
    },
    {
        "worldSetNo": 2,
        "routeId": 100030,
        "imgId": 100030,
        "posX": 1054,
        "posY": 736,
        "flag1Id": 31104021,
        "flag2Id": 0,
        "flag3Id": 0,
        "searchText": "USA_インド"
    },
    {
        "worldSetNo": 2,
        "routeId": 100040,
        "imgId": 100040,
        "posX": 1307,
        "posY": 857,
        "flag1Id": 999999,
        "flag2Id": 0,
        "flag3Id": 0,
        "searchText": "USA_カルカッタ_アユタヤ"
    },
    {
        "worldSetNo": 2,
        "routeId": 100050,
        "imgId": 100050,
        "posX": 2193,
        "posY": 598,
        "flag1Id": 31107021,
        "flag2Id": 0,
        "flag3Id": 0,
        "searchText": "USA_サンフランシスコ_ハワイ"
    },
    {
        "worldSetNo": 2,
        "routeId": 100060,
        "imgId": 100060,
        "posX": 2169,
        "posY": 800,
        "flag1Id": 999999,
        "flag2Id": 0,
        "flag3Id": 0,
        "searchText": "USA_タヒチ_ハワイ"
    },
    {
        "worldSetNo": 2,
        "routeId": 100070,
        "imgId": 100070,
        "posX": 2597,
        "posY": 675,
        "flag1Id": 31107091,
        "flag2Id": 0,
        "flag3Id": 0,
        "searchText": "USA_チワワ_テオティワカン"
    },
    {
        "worldSetNo": 2,
        "routeId": 100080,
        "imgId": 100080,
        "posX": 2785,
        "posY": 858,
        "flag1Id": 31108041,
        "flag2Id": 0,
        "flag3Id": 0,
        "searchText": "USA_パナマ_キト"
    },
    {
        "worldSetNo": 2,
        "routeId": 100090,
        "imgId": 100090,
        "posX": -539,
        "posY": 312,
        "flag1Id": 999999,
        "flag2Id": 0,
        "flag3Id": 0,
        "searchText": "USA_ブリタニア"
    },
    {
        "worldSetNo": 2,
        "routeId": 100100,
        "imgId": 100100,
        "posX": 3005,
        "posY": 312,
        "flag1Id": 999999,
        "flag2Id": 0,
        "flag3Id": 0,
        "searchText": "USA_ブリタニアa"
    },
    {
        "worldSetNo": 2,
        "routeId": 100110,
        "imgId": 100110,
        "posX": 270,
        "posY": 630,
        "flag1Id": 999999,
        "flag2Id": 0,
        "flag3Id": 0,
        "searchText": "USA_暗黒領域"
    },
    {
        "worldSetNo": 2,
        "routeId": 100120,
        "imgId": 100120,
        "posX": -544,
        "posY": 203,
        "flag1Id": 999999,
        "flag2Id": 0,
        "flag3Id": 0,
        "searchText": "USA_欧州"
    },
    {
        "worldSetNo": 2,
        "routeId": 100130,
        "imgId": 100130,
        "posX": 3000,
        "posY": 203,
        "flag1Id": 999999,
        "flag2Id": 0,
        "flag3Id": 0,
        "searchText": "USA_欧州a"
    },
    {
        "worldSetNo": 2,
        "routeId": 100150,
        "imgId": 100150,
        "posX": 1731,
        "posY": 726,
        "flag1Id": 31106011,
        "flag2Id": 0,
        "flag3Id": 0,
        "searchText": "USA_邪馬台_グァム"
    },
    {
        "worldSetNo": 2,
        "routeId": 100160,
        "imgId": 100160,
        "posX": 1644,
        "posY": 487,
        "flag1Id": 31103011,
        "flag2Id": 0,
        "flag3Id": 0,
        "searchText": "USA_邪馬台_ザナドゥ"
    },
    {
        "worldSetNo": 2,
        "routeId": 100170,
        "imgId": 100170,
        "posX": 1574,
        "posY": 727,
        "flag1Id": 31101061,
        "flag2Id": 0,
        "flag3Id": 0,
        "searchText": "USA_邪馬台_香港"
    },
    {
        "worldSetNo": 2,
        "routeId": 100180,
        "imgId": 100180,
        "posX": 1661,
        "posY": 725,
        "flag1Id": 31102011,
        "flag2Id": 0,
        "flag3Id": 0,
        "searchText": "USA_邪馬台_上海"
    },
    {
        "worldSetNo": 2,
        "routeId": 100190,
        "imgId": 100190,
        "posX": 1858,
        "posY": 597,
        "flag1Id": 999999,
        "flag2Id": 0,
        "flag3Id": 0,
        "searchText": "USA_仙台_サンフランシスコ"
    },
    {
        "worldSetNo": 2,
        "routeId": 100200,
        "imgId": 100200,
        "posX": 1289,
        "posY": 527,
        "flag1Id": 31102021,
        "flag2Id": 0,
        "flag3Id": 0,
        "searchText": "USA_大華帝国"
    },
    {
        "worldSetNo": 2,
        "routeId": 100210,
        "imgId": 100210,
        "posX": 851,
        "posY": 659,
        "flag1Id": 999999,
        "flag2Id": 0,
        "flag3Id": 0,
        "searchText": "USA_中東"
    },
    {
        "worldSetNo": 2,
        "routeId": 100220,
        "imgId": 100220,
        "posX": 2852,
        "posY": 1222,
        "flag1Id": 999999,
        "flag2Id": 0,
        "flag3Id": 0,
        "searchText": "USA_南米_大西洋"
    },
    {
        "worldSetNo": 2,
        "routeId": 100240,
        "imgId": 100240,
        "posX": 2284,
        "posY": 246,
        "flag1Id": 31107031,
        "flag2Id": 0,
        "flag3Id": 0,
        "searchText": "USA_北米１"
    },
    {
        "worldSetNo": 2,
        "routeId": 100250,
        "imgId": 100250,
        "posX": 2607,
        "posY": 550,
        "flag1Id": 31107041,
        "flag2Id": 0,
        "flag3Id": 0,
        "searchText": "USA_北米２"
    },
    {
        "worldSetNo": 2,
        "routeId": 100260,
        "imgId": 100260,
        "posX": 2757,
        "posY": 525,
        "flag1Id": 31107081,
        "flag2Id": 0,
        "flag3Id": 0,
        "searchText": "USA_北米３"
    },
    {
        "worldSetNo": 2,
        "routeId": 100270,
        "imgId": 100270,
        "posX": 2835,
        "posY": 730,
        "flag1Id": 31125021,
        "flag2Id": 0,
        "flag3Id": 0,
        "searchText": "ヴィンランド"
    },
    {
        "worldSetNo": 2,
        "routeId": 100280,
        "imgId": 100280,
        "posX": 585,
        "posY": 772,
        "flag1Id": 31122031,
        "flag2Id": 0,
        "flag3Id": 0,
        "searchText": "エジプト"
    },
    {
        "worldSetNo": 2,
        "routeId": 100290,
        "imgId": 100290,
        "posX": 640,
        "posY": 725,
        "flag1Id": 31122021,
        "flag2Id": 0,
        "flag3Id": 0,
        "searchText": "エジプト２"
    },
    {
        "worldSetNo": 2,
        "routeId": 100300,
        "imgId": 100300,
        "posX": 3168,
        "posY": 614,
        "flag1Id": 999999,
        "flag2Id": 0,
        "flag3Id": 0,
        "searchText": "エリュシオン_アトランティス"
    },
    {
        "worldSetNo": 2,
        "routeId": 100310,
        "imgId": 100310,
        "posX": 2984,
        "posY": 772,
        "flag1Id": 999999,
        "flag2Id": 0,
        "flag3Id": 0,
        "searchText": "サントドミンゴ_エリュシオン"
    },
    {
        "worldSetNo": 2,
        "routeId": 100320,
        "imgId": 100320,
        "posX": 1732,
        "posY": 624,
        "flag1Id": 31101021,
        "flag2Id": 0,
        "flag3Id": 0,
        "searchText": "ジパング"
    },
    {
        "worldSetNo": 2,
        "routeId": 100330,
        "imgId": 100330,
        "posX": 568,
        "posY": 166,
        "flag1Id": 999999,
        "flag2Id": 0,
        "flag3Id": 0,
        "searchText": "ストックホルム_ヒュペルボレイオス"
    },
    {
        "worldSetNo": 2,
        "routeId": 100340,
        "imgId": 100340,
        "posX": 2577,
        "posY": 508,
        "flag1Id": 999999,
        "flag2Id": 0,
        "flag3Id": 0,
        "searchText": "ソルトレイクシティ_エルピス_ＵＳＡ"
    },
    {
        "worldSetNo": 2,
        "routeId": 100350,
        "imgId": 100350,
        "posX": 322,
        "posY": 268,
        "flag1Id": 31110011,
        "flag2Id": 0,
        "flag3Id": 0,
        "searchText": "ブリタニア"
    },
    {
        "worldSetNo": 2,
        "routeId": 100360,
        "imgId": 100360,
        "posX": 1021,
        "posY": 917,
        "flag1Id": 999999,
        "flag2Id": 0,
        "flag3Id": 0,
        "searchText": "ムンバイ_ドワール・カー"
    },
    {
        "worldSetNo": 2,
        "routeId": 100370,
        "imgId": 100370,
        "posX": 1037,
        "posY": 462,
        "flag1Id": 31103041,
        "flag2Id": 0,
        "flag3Id": 0,
        "searchText": "ルート_アルマリク_ウルゲンチ"
    },
    {
        "worldSetNo": 2,
        "routeId": 100380,
        "imgId": 100380,
        "posX": 1989,
        "posY": 287,
        "flag1Id": 999999,
        "flag2Id": 0,
        "flag3Id": 0,
        "searchText": "ルート_アンカレジ_カムチャッキー"
    },
    {
        "worldSetNo": 2,
        "routeId": 100390,
        "imgId": 100390,
        "posX": 687,
        "posY": 562,
        "flag1Id": 999999,
        "flag2Id": 0,
        "flag3Id": 0,
        "searchText": "ルート_コンスタンティノープル_ゴルディオン"
    },
    {
        "worldSetNo": 2,
        "routeId": 100400,
        "imgId": 100400,
        "posX": 678,
        "posY": 193,
        "flag1Id": 999999,
        "flag2Id": 0,
        "flag3Id": 0,
        "searchText": "ルート_サンクトペテルブルグ_ヘルシンキ"
    },
    {
        "worldSetNo": 2,
        "routeId": 100410,
        "imgId": 100410,
        "posX": 2834,
        "posY": 550,
        "flag1Id": 31125011,
        "flag2Id": 0,
        "flag3Id": 0,
        "searchText": "ルート_ニューヨーク_ハバナ"
    },
    {
        "worldSetNo": 2,
        "routeId": 100420,
        "imgId": 100420,
        "posX": 587,
        "posY": 849,
        "flag1Id": 999999,
        "flag2Id": 0,
        "flag3Id": 0,
        "searchText": "隠し_アアル"
    },
    {
        "worldSetNo": 2,
        "routeId": 100430,
        "imgId": 100430,
        "posX": 209,
        "posY": 267,
        "flag1Id": 999999,
        "flag2Id": 0,
        "flag3Id": 0,
        "searchText": "隠し_アヴァロン"
    },
    {
        "worldSetNo": 2,
        "routeId": 100440,
        "imgId": 100440,
        "posX": 318,
        "posY": 397,
        "flag1Id": 31111011,
        "flag2Id": 0,
        "flag3Id": 0,
        "searchText": "隠し_イース"
    },
    {
        "worldSetNo": 2,
        "routeId": 100450,
        "imgId": 100450,
        "posX": 2858,
        "posY": 1093,
        "flag1Id": 999999,
        "flag2Id": 0,
        "flag3Id": 0,
        "searchText": "隠し_エル・ドラードゲート"
    },
    {
        "worldSetNo": 2,
        "routeId": 100460,
        "imgId": 100460,
        "posX": 770,
        "posY": 531,
        "flag1Id": 999999,
        "flag2Id": 0,
        "flag3Id": 0,
        "searchText": "隠し_カイマクル"
    },
    {
        "worldSetNo": 2,
        "routeId": 100480,
        "imgId": 100480,
        "posX": 1017,
        "posY": 942,
        "flag1Id": 999999,
        "flag2Id": 0,
        "flag3Id": 0,
        "searchText": "隠し_クマリナドゥ"
    },
    {
        "worldSetNo": 2,
        "routeId": 100490,
        "imgId": 100490,
        "posX": 875,
        "posY": 455,
        "flag1Id": 999999,
        "flag2Id": 0,
        "flag3Id": 0,
        "searchText": "隠し_シャンバラ"
    },
    {
        "worldSetNo": 2,
        "routeId": 100500,
        "imgId": 100500,
        "posX": 483,
        "posY": 595,
        "flag1Id": 999999,
        "flag2Id": 0,
        "flag3Id": 0,
        "searchText": "隠し_シュオル"
    },
    {
        "worldSetNo": 2,
        "routeId": 100510,
        "imgId": 100510,
        "posX": 2155,
        "posY": 896,
        "flag1Id": 999999,
        "flag2Id": 0,
        "flag3Id": 0,
        "searchText": "隠し_ヒラニプラ"
    },
    {
        "worldSetNo": 2,
        "routeId": 100520,
        "imgId": 100520,
        "posX": 572,
        "posY": 90,
        "flag1Id": 999999,
        "flag2Id": 0,
        "flag3Id": 0,
        "searchText": "隠し_ポホヨラ"
    },
    {
        "worldSetNo": 2,
        "routeId": 100530,
        "imgId": 100530,
        "posX": 2995,
        "posY": 245,
        "flag1Id": 999999,
        "flag2Id": 0,
        "flag3Id": 0,
        "searchText": "隠し_マグ・メル"
    },
    {
        "worldSetNo": 2,
        "routeId": 100540,
        "imgId": 100540,
        "posX": 1732,
        "posY": 669,
        "flag1Id": 999999,
        "flag2Id": 0,
        "flag3Id": 0,
        "searchText": "隠し_竜宮"
    },
    {
        "worldSetNo": 2,
        "routeId": 100560,
        "imgId": 100560,
        "posX": 821,
        "posY": 717,
        "flag1Id": 999999,
        "flag2Id": 0,
        "flag3Id": 0,
        "searchText": "中東"
    },
    {
        "worldSetNo": 2,
        "routeId": 100570,
        "imgId": 100570,
        "posX": 2627,
        "posY": 723,
        "flag1Id": 31108011,
        "flag2Id": 0,
        "flag3Id": 0,
        "searchText": "南米"
    },
    {
        "worldSetNo": 2,
        "routeId": 100580,
        "imgId": 100580,
        "posX": 643,
        "posY": 463,
        "flag1Id": 999999,
        "flag2Id": 0,
        "flag3Id": 0,
        "searchText": "馬蒙連合"
    },
    {
        "worldSetNo": 2,
        "routeId": 100590,
        "imgId": 100590,
        "posX": 1275,
        "posY": 856,
        "flag1Id": 31104011,
        "flag2Id": 0,
        "flag3Id": 0,
        "searchText": "ルート_香港_カルカッタ"
    },
    {
        "worldSetNo": 2,
        "routeId": 100600,
        "imgId": 100600,
        "posX": 645,
        "posY": 547,
        "flag1Id": 31121011,
        "flag2Id": 0,
        "flag3Id": 0,
        "searchText": "ルート_マケドニア"
    },
    {
        "worldSetNo": 2,
        "routeId": 100610,
        "imgId": 100610,
        "posX": 1058,
        "posY": 465,
        "flag1Id": 31103021,
        "flag2Id": 0,
        "flag3Id": 0,
        "searchText": "ルート_モンゴル"
    },
    {
        "worldSetNo": 2,
        "routeId": 100620,
        "imgId": 100620,
        "posX": 2834,
        "posY": 1387,
        "flag1Id": 31108061,
        "flag2Id": 0,
        "flag3Id": 0,
        "searchText": "ルート_バルパライソ_ブエノスアイレス"
    },
    {
        "worldSetNo": 2,
        "routeId": 100630,
        "imgId": 100630,
        "posX": 3042,
        "posY": 1226,
        "flag1Id": 31108061,
        "flag2Id": 0,
        "flag3Id": 0,
        "searchText": "ルート_ブエノスアイレス_リオデジャネイロ"
    },
    {
        "worldSetNo": 2,
        "routeId": 100640,
        "imgId": 100640,
        "posX": 250,
        "posY": 203,
        "flag1Id": 31109011,
        "flag2Id": 0,
        "flag3Id": 0,
        "searchText": "欧州"
    },
    {
        "worldSetNo": 2,
        "routeId": 100650,
        "imgId": 100650,
        "posX": 3205,
        "posY": 520,
        "flag1Id": 31108081,
        "flag2Id": 0,
        "flag3Id": 0,
        "searchText": "ルート_リオデジャネイロ_リスボン"
    },
    {
        "worldSetNo": 2,
        "routeId": 100660,
        "imgId": 100660,
        "posX": 1858,
        "posY": 624,
        "flag1Id": 31107011,
        "flag2Id": 0,
        "flag3Id": 0,
        "searchText": "ルート_仙台_ハワイ"
    },
    {
        "worldSetNo": 2,
        "routeId": 100670,
        "imgId": 100670,
        "posX": 1639,
        "posY": 480,
        "flag1Id": 31123011,
        "flag2Id": 0,
        "flag3Id": 0,
        "searchText": "ルート_ザナドゥ_ウラジオストック"
    },
    {
        "worldSetNo": 2,
        "routeId": 100680,
        "imgId": 100680,
        "posX": 865,
        "posY": 840,
        "flag1Id": 31112031,
        "flag2Id": 0,
        "flag3Id": 0,
        "searchText": "隠し_エルピス_バベル"
    },
    {
        "worldSetNo": 2,
        "routeId": 100690,
        "imgId": 100690,
        "posX": 630,
        "posY": 590,
        "flag1Id": 31112011,
        "flag2Id": 0,
        "flag3Id": 0,
        "searchText": "ルート_ウルク_アテネ"
    },
    {
        "worldSetNo": 2,
        "routeId": 100700,
        "imgId": 100700,
        "posX": 821,
        "posY": 777,
        "flag1Id": 31112021,
        "flag2Id": 0,
        "flag3Id": 0,
        "searchText": "中東２"
    },
    {
        "worldSetNo": 2,
        "routeId": 100710,
        "imgId": 100710,
        "posX": 1485,
        "posY": 930,
        "flag1Id": 31106021,
        "flag2Id": 0,
        "flag3Id": 0,
        "searchText": "南洋２"
    },
    {
        "worldSetNo": 10030,
        "routeId": 100720,
        "imgId": 100720,
        "posX": 1505,
        "posY": 1232,
        "flag1Id": 33101021,
        "flag2Id": 0,
        "flag3Id": 0,
        "searchText": "オーストラリア本土"
    },
    {
        "worldSetNo": 10030,
        "routeId": 100730,
        "imgId": 100730,
        "posX": 1685,
        "posY": 726,
        "flag1Id": 33101010,
        "flag2Id": 0,
        "flag3Id": 0,
        "searchText": "邪馬台～オーストラリア"
    }
]